colocationship/__init__.py
colocationship/meetup_comparison.py
colocationship/meetup_fast.py
colocationship/meetup_strategy.py
colocationship/util/__init__.py
colocationship/util/cross_entropy.py
colocationship/util/cumulative_cross_entropy.py
colocationship/util/entropy.py
colocationship/util/metric.py
colocationship/util/predictability.py
colocationship/util/preprocessing.py
colocationship/util/stats_test.py
colocationship/util/utils.py
colocationship-2.0.dist-info/LICENSE
colocationship-2.0.dist-info/METADATA
colocationship-2.0.dist-info/WHEEL
colocationship-2.0.dist-info/top_level.txt
colocationship-2.0.dist-info/RECORD
