Metadata-Version: 2.1
Name: colocationship
Version: 2.0
Summary: A light package for build and analyse co-locationship for paper: Contrasting social and non-social sources of predictability in human mobility
Home-page: https://github.com/Magica-Chen/co-locationship
Author: Zexun Chen
Author-email: sxtpy2010@gmail.com
License: UNKNOWN
Platform: UNKNOWN
Classifier: Programming Language :: Python :: 3
Classifier: License :: OSI Approved :: MIT License
Classifier: Operating System :: OS Independent
Requires-Python: >=3.6
License-File: LICENSE
